{
  "_id": "lieu-2015-12-06-16-15-29-86966191755",
  "breadcrumb": "lieux/ville/Canada/Territoires-du-Nord-Ouest/Fort-Smith/",
  "fiche-publiee": true,
  "mise-a-jour": "2016-04-16-01-36-56",
  "moment-de-creation": "2015-12-06-16-15-29",
  "nom": "Fort Smith (Territoires-du-Nord-Ouest)",
  "nom-folder": "Fort-Smith",
  "nom-machine": "lieu-2015-12-06-16-15-29-86966191755",
  "sous-type": "ville",
  "type": "lieux",
  "nomLangues": {
    "fr": [
      "Fort Smith (Territoires-du-Nord-Ouest)"
    ]
  }
}