{
  "_id": "lieu-2015-12-06-16-10-49-86966174960",
  "ajouter-aux-favoris": false,
  "breadcrumb": "lieux/monde/Test-ete-allo/Sous-terme/",
  "copyright": false,
  "description": "Sous terme",
  "fiche-a-completer": true,
  "fiche-publiee": true,
  "mise-a-jour": "2015-11-08-22-57-42",
  "moment-de-creation": "2015-12-06-16-10-49",
  "moment-de-modification": "2015-11-08-22-57-42",
  "nom": "Sous terme",
  "nom-folder": "Sous-terme",
  "nom-machine": "lieu-2015-12-06-16-10-49-86966174960",
  "sous-type": "monde",
  "type": "lieux",
  "nomLangues": {
    "en": [
      "Child"
    ],
    "fr": [
      "Sous terme"
    ]
  }
}