{
  "_id": "lieu-2015-12-06-16-14-43-86966188995",
  "breadcrumb": "lieux/ville/Canada/Quebec/Notre-Dame-du-Sacre-Coeur-d'Issoudun/",
  "fiche-publiee": true,
  "mise-a-jour": "2016-04-16-01-36-56",
  "moment-de-creation": "2015-12-06-16-14-43",
  "nom": "Notre-Dame-du-Sacré-Cœur-d'Issoudun",
  "nom-folder": "Notre-Dame-du-Sacre-Coeur-d'Issoudun",
  "nom-machine": "lieu-2015-12-06-16-14-43-86966188995",
  "sous-type": "ville",
  "type": "lieux",
  "nomLangues": {
    "fr": [
      "Notre-Dame-du-Sacré-Cœur-d'Issoudun"
    ]
  }
}