{
  "_id": "lieu-2015-12-06-16-18-00-86966200823",
  "breadcrumb": "lieux/ville/France/Corse-du-Sud/Castellare-di-Mercurio-(CdS)/",
  "fiche-publiee": true,
  "mise-a-jour": "2016-04-16-01-36-56",
  "moment-de-creation": "2015-12-06-16-18-00",
  "nom": "Castellare-di-Mercurio (CdS)",
  "nom-folder": "Castellare-di-Mercurio-(CdS)",
  "nom-machine": "lieu-2015-12-06-16-18-00-86966200823",
  "sous-type": "ville",
  "type": "lieux",
  "nomLangues": {
    "fr": [
      "Castellare-di-Mercurio (CdS)"
    ]
  }
}