{
  "_id": "lieu-2015-12-06-16-14-45-86966189131",
  "breadcrumb": "lieux/reserve/Canada/Quebec/Quaqtaq-(terre-reservee-inuit)/",
  "fiche-publiee": true,
  "mise-a-jour": "2016-04-16-01-36-56",
  "moment-de-creation": "2015-12-06-16-14-45",
  "nom": "Quaqtaq (terre réservée inuit)",
  "nom-folder": "Quaqtaq-(terre-reservee-inuit)",
  "nom-machine": "lieu-2015-12-06-16-14-45-86966189131",
  "sous-type": "reserve",
  "type": "lieux",
  "nomLangues": {
    "fr": [
      "Quaqtaq (terre réservée inuit)"
    ]
  }
}