{
  "_id": "lieu-2015-12-06-16-18-05-86966201139",
  "breadcrumb": "lieux/ville/France/Corse-du-Sud/Prunelli-di-Casacconi-(CdS)/",
  "fiche-publiee": true,
  "mise-a-jour": "2016-04-16-01-36-56",
  "moment-de-creation": "2015-12-06-16-18-05",
  "nom": "Prunelli-di-Casacconi (CdS)",
  "nom-folder": "Prunelli-di-Casacconi-(CdS)",
  "nom-machine": "lieu-2015-12-06-16-18-05-86966201139",
  "sous-type": "ville",
  "type": "lieux",
  "nomLangues": {
    "fr": [
      "Prunelli-di-Casacconi (CdS)"
    ]
  }
}