{
  "_id": "pers-2016-03-25-07-02-36-87534225368",
  "ajouter-aux-favoris": false,
  "date-edition": "2016-03-25-07-02-36",
  "fiche-a-completer": true,
  "fiche-publiee": true,
  "identifiant-drupal": 463015,
  "importance": 0,
  "langue-edition": [
    "terme-2015-12-06-16-10-40-86966174431"
  ],
  "mise-a-jour": "2016-05-09-16-44-11",
  "moment-de-creation": "2016-03-25-07-02-36",
  "moment-de-modification": "2016-03-25-07-02-36",
  "nom": "Duncan Howe",
  "nom-machine": [
    "pers-2016-03-25-07-02-36-87534225368"
  ],
  "personne-nom-famille": "Howe",
  "personne-nom-prenom": "Duncan ",
  "site-de-diffusion": [
    "terme-2015-12-06-16-23-47-86966221646"
  ],
  "source-defectueuse": false,
  "source-url": "http://www.phdadministration.net/?id=pers-2016-03-25-07-02-36-87534225368",
  "sous-type": "pers",
  "tip": "SCS-459496",
  "type": "ressources",
  "type-de-ressource": [
    "terme-2015-12-06-16-27-16-86966234209",
    "terme-2015-12-06-16-27-18-86966234335",
    "terme-2015-12-06-16-27-21-86966234485"
  ],
  "nomLangues": {
    "fr": [
      "Duncan Howe"
    ]
  }
}