{
  "_id": "pers-2016-03-25-06-59-35-87534214512",
  "ajouter-aux-favoris": false,
  "date-edition": "2016-03-25-06-59-35",
  "fiche-a-completer": true,
  "fiche-publiee": true,
  "identifiant-drupal": 4262,
  "importance": 0,
  "mise-a-jour": "2017-01-22-15-48-57",
  "moment-de-creation": "2016-03-25-06-59-35",
  "moment-de-modification": "2016-03-25-06-59-35",
  "nom": "Robert Castel",
  "nom-machine": [
    "pers-2016-03-25-06-59-35-87534214512"
  ],
  "personne-nom-famille": "Castel",
  "personne-nom-prenom": "Robert",
  "site-de-diffusion": [
    "terme-2015-12-06-16-23-47-86966221646"
  ],
  "source-defectueuse": false,
  "source-url": "http://www.phdadministration.net/personne/pers-2016-03-25-06-59-35-87534214512",
  "sous-type": "pers",
  "type": "ressources",
  "type-de-ressource": [
    "terme-2015-12-06-16-27-16-86966234209",
    "terme-2015-12-06-16-27-18-86966234335"
  ],
  "nomLangues": {
    "fr": [
      "Robert Castel"
    ]
  }
}