{
  "_id": "terme-2015-12-06-16-26-17-86966230676",
  "ajouter-aux-favoris": false,
  "breadcrumb": "taxonomies/sujets/Sciences-exactes/Mathematiques/Dessin-d'enfant/",
  "description": "Dessin d'enfant",
  "fiche-a-completer": true,
  "fiche-publiee": true,
  "identifiant-drupal": 466913,
  "identifiant-drupal-parent": 272243,
  "mise-a-jour": "2016-05-09-16-46-29",
  "moment-de-creation": "2015-12-06-16-26-17",
  "moment-de-modification": "2015-01-04-02-27-37",
  "nom": "Dessin d'enfant (graphe)",
  "nom-folder": "Dessin-d'enfant",
  "nom-machine": "terme-2015-12-06-16-26-17-86966230676",
  "sous-type": "sujets",
  "type": "taxonomies",
  "nomLangues": {
    "en": [
      "Dessin d'enfant (mathematics)"
    ],
    "ar": [
      "رسم الطفل )كروثنديك("
    ],
    "es": [
      "Dessin d'enfant (gráfico)"
    ],
    "fr": [
      "Dessin d'enfant (graphe)"
    ],
    "it": [
      "Disegno di bambino (grafico)"
    ]
  }
}