{
  "_id": "terme-2015-12-06-16-25-37-86966228262",
  "ajouter-aux-favoris": false,
  "breadcrumb": "taxonomies/sujets/Sciences-de-la-gestion/Branches-des-sciences-de-la-gestion/Gestion-du-changement-(gestion)/Conduite-du-changement/",
  "description": "Description de Conduite du changement",
  "fiche-a-completer": false,
  "fiche-publiee": true,
  "identifiant-drupal": 2013,
  "identifiant-drupal-parent": 2008,
  "mise-a-jour": "2017-01-23-16-33-30",
  "moment-de-creation": "2015-12-06-16-25-37",
  "moment-de-modification": "2015-01-04-02-27-41",
  "nom": "Conduite du changement",
  "nom-folder": "Conduite-du-changement",
  "nom-machine": "terme-2015-12-06-16-25-37-86966228262",
  "parent": "terme-2015-12-06-16-25-37-86966228252",
  "sous-type": "sujets",
  "type": "taxonomies",
  "nomLangues": {
    "en": [
      "Change management"
    ],
    "ar": [
      "تسيير إلى التغيير"
    ],
    "es": [
      "Gestión del Cambio"
    ],
    "fr": [
      "Conduite du changement"
    ],
    "it": [
      "Gestione del cambiamento"
    ]
  }
}