{
  "_id": "terme-2015-12-06-16-25-00-86966226022",
  "ajouter-aux-favoris": false,
  "breadcrumb": "taxonomies/sujets/Informatique/Ingenierie-informatique/",
  "description": "Description de Ingénierie informatique",
  "fiche-a-completer": true,
  "fiche-publiee": true,
  "identifiant-drupal": 271403,
  "identifiant-drupal-parent": 879,
  "mise-a-jour": "2016-05-09-16-46-12",
  "moment-de-creation": "2015-12-06-16-25-00",
  "moment-de-modification": "2015-01-04-02-27-45",
  "nom": "Ingénierie informatique",
  "nom-folder": "Ingenierie-informatique",
  "nom-machine": [
    "terme-2015-12-06-16-25-00-86966226022"
  ],
  "sous-type": "sujets",
  "type": "taxonomies",
  "nomLangues": {
    "en": [
      "Computer Engineering"
    ],
    "ar": [
      "هندسة الكمبيوتر"
    ],
    "es": [
      "Ingeniería informática"
    ],
    "fr": [
      "Ingénierie informatique"
    ],
    "it": [
      "Ingegneria informatica"
    ]
  }
}