{
  "_id": "terme-2015-12-06-16-25-47-86966228832",
  "ajouter-aux-favoris": false,
  "breadcrumb": "taxonomies/sujets/Sciences-de-la-gestion/Branches-des-sciences-de-la-gestion/Ressources-humaines-et-organisation/Gestion-de-la-performance/",
  "description": "Description de Gestion de la performance",
  "enfants": [
    "terme-2015-12-06-16-25-47-86966228835",
    "terme-2015-12-06-16-25-47-86966228839",
    "terme-2015-12-06-16-25-47-86966228842"
  ],
  "fiche-a-completer": false,
  "fiche-publiee": true,
  "identifiant-drupal": 2121,
  "identifiant-drupal-parent": 2105,
  "mise-a-jour": "2017-01-23-16-33-30",
  "moment-de-creation": "2015-12-06-16-25-47",
  "moment-de-modification": "2015-01-04-02-27-40",
  "nom": "Gestion de la performance",
  "nom-folder": "Gestion-de-la-performance",
  "nom-machine": [
    "terme-2015-12-06-16-25-47-86966228832"
  ],
  "parent": "terme-2015-12-06-16-25-45-86966228732",
  "sous-type": "sujets",
  "type": "taxonomies",
  "nomLangues": {
    "en": [
      "Performance management"
    ],
    "ar": [
      "إدارة الأداء"
    ],
    "es": [
      "Gestión del rendimiento"
    ],
    "fr": [
      "Gestion de la performance"
    ],
    "it": [
      "gestione delle prestazioni"
    ]
  }
}