{
  "_id": "terme-2015-12-06-16-23-59-86966222348",
  "ajouter-aux-favoris": false,
  "breadcrumb": "taxonomies/sujets-JournalSeek/Economics/Econ-Dev,-Technological-Change-and-Growth/",
  "description": "Description de Econ dev, technological change and growth",
  "fiche-a-completer": false,
  "fiche-publiee": true,
  "identifiant-drupal": 368936,
  "identifiant-drupal-parent": 368932,
  "mise-a-jour": "2017-01-23-16-33-30",
  "moment-de-creation": "2015-12-06-16-23-59",
  "moment-de-modification": "2015-01-04-02-26-18",
  "nom": "Econ dev, technological change and growth",
  "nom-folder": "Econ-Dev,-Technological-Change-and-Growth",
  "nom-machine": "terme-2015-12-06-16-23-59-86966222348",
  "parent": "terme-2015-12-06-16-23-58-86966222338",
  "sous-type": "sujets-JournalSeek",
  "type": "taxonomies",
  "nomLangues": {
    "fr": [
      "Econ dev, technological change and growth"
    ]
  }
}