{
  "_id": "terme-2015-12-06-16-24-19-86966223579",
  "ajouter-aux-favoris": false,
  "breadcrumb": "taxonomies/sujets-sage/Health-Sciences/Allied-Health/",
  "description": "Description de Professions paramédicales",
  "fiche-a-completer": false,
  "fiche-publiee": true,
  "identifiant-drupal": 368148,
  "identifiant-drupal-parent": 368144,
  "mise-a-jour": "2017-01-23-16-33-30",
  "moment-de-creation": "2015-12-06-16-24-19",
  "moment-de-modification": "2015-01-04-02-27-33",
  "nom": "Professions paramédicales",
  "nom-folder": "Allied-Health",
  "nom-machine": "terme-2015-12-06-16-24-19-86966223579",
  "parent": "terme-2015-12-06-16-24-19-86966223576",
  "sous-type": "sujets-sage",
  "type": "taxonomies",
  "nomLangues": {
    "en": [
      "Allied health"
    ],
    "fr": [
      "Professions paramédicales"
    ]
  }
}