{
  "_id": "terme-2015-12-06-16-24-40-86966224854",
  "ajouter-aux-favoris": false,
  "breadcrumb": "taxonomies/sujets/Art/Gravure/Techniques-de-la-gravure/Gravure-en-relief/",
  "description": "Description de Gravure en relief",
  "fiche-a-completer": false,
  "fiche-publiee": true,
  "identifiant-drupal": 466938,
  "identifiant-drupal-parent": 466929,
  "mise-a-jour": "2017-01-23-16-33-30",
  "moment-de-creation": "2015-12-06-16-24-40",
  "moment-de-modification": "2015-01-04-02-27-50",
  "nom": "Gravure en relief",
  "nom-folder": "Gravure-en-relief",
  "nom-machine": "terme-2015-12-06-16-24-40-86966224854",
  "parent": "terme-2015-12-06-16-24-40-86966224837",
  "sous-type": "sujets",
  "type": "taxonomies",
  "nomLangues": {
    "en": [
      "Relief print"
    ],
    "ar": [
      "نقش مجسم"
    ],
    "es": [
      "Grabado en relieve"
    ],
    "fr": [
      "Gravure en relief"
    ],
    "it": [
      "Incisione in rilievo"
    ]
  }
}