{
  "_id": "terme-2015-12-06-16-25-18-86966227103",
  "ajouter-aux-favoris": false,
  "breadcrumb": "taxonomies/sujets/Sciences-de-la-gestion/Administration-des-affaires/Faillite/",
  "description": "Description de Faillite",
  "fiche-a-completer": false,
  "fiche-publiee": true,
  "identifiant-drupal": 472180,
  "identifiant-drupal-parent": 467199,
  "mise-a-jour": "2017-01-23-16-33-30",
  "moment-de-creation": "2015-12-06-16-25-18",
  "moment-de-modification": "2015-01-04-02-27-44",
  "nom": "Faillite",
  "nom-folder": "Faillite",
  "nom-machine": [
    "terme-2015-12-06-16-25-18-86966227103"
  ],
  "parent": "terme-2015-12-06-16-25-17-86966227065",
  "sous-type": "sujets",
  "type": "taxonomies",
  "nomLangues": {
    "en": [
      "Bankruptcy"
    ],
    "ar": [
      "إفلاس"
    ],
    "es": [
      "Quiebra"
    ],
    "fr": [
      "Faillite"
    ],
    "it": [
      "Fallimento"
    ]
  }
}