{
  "_id": "terme-2015-12-06-16-23-31-86966220690",
  "ajouter-aux-favoris": false,
  "breadcrumb": "taxonomies/sections/Entreprise/Industries/Industrie-agroalimentaire/",
  "description": "Description de Industrie agroalimentaire",
  "fiche-a-completer": false,
  "fiche-publiee": true,
  "identifiant-drupal": 270593,
  "identifiant-drupal-parent": 270556,
  "mise-a-jour": "2016-05-09-16-45-52",
  "moment-de-creation": "2015-12-06-16-23-31",
  "moment-de-modification": "2015-01-04-02-27-34",
  "nom": "Industrie agroalimentaire",
  "nom-folder": "Industrie-agroalimentaire",
  "nom-machine": [
    "terme-2015-12-06-16-23-31-86966220690"
  ],
  "sous-type": "sections",
  "type": "taxonomies",
  "nomLangues": {
    "en": [
      "Agribusiness"
    ],
    "ar": [
      "الاعمال التجارية الزراعية"
    ],
    "es": [
      "Agroindustria"
    ],
    "fr": [
      "Industrie agroalimentaire"
    ],
    "it": [
      "Industria agroalimentare"
    ],
    "ru": [
      "агробизнес"
    ]
  }
}