{
  "_id": "terme-2015-12-06-16-10-44-86966174697",
  "ajouter-aux-favoris": false,
  "breadcrumb": "taxonomies/langues/Norvegien/Norvegien-bokmal/",
  "description": "Norvégien bokmål",
  "fiche-a-completer": false,
  "fiche-publiee": true,
  "identifiant-drupal": 317635,
  "mise-a-jour": "2017-01-23-16-33-30",
  "moment-de-creation": "2015-12-06-16-10-44",
  "moment-de-modification": "2015-01-04-02-27-57",
  "nom": "Bokmål",
  "nom-folder": "Norvegien-bokmal",
  "nom-machine": "terme-2015-12-06-16-10-44-86966174697",
  "parent": "terme-2015-12-06-16-10-44-86966174691",
  "sous-type": "langues",
  "type": "taxonomies",
  "nomLangues": {
    "en": [
      "Norwegian bokmål"
    ],
    "ar": [
      "بوكمول"
    ],
    "es": [
      "Bokmål"
    ],
    "fr": [
      "Bokmål"
    ],
    "it": [
      "Bokmål"
    ],
    "ru": [
      "Букмол"
    ]
  }
}