{
  "_id": "terme-2015-12-06-16-25-58-86966229500",
  "ajouter-aux-favoris": false,
  "breadcrumb": "taxonomies/sujets/Sciences-de-la-gestion/Branches-des-sciences-de-la-gestion/Theories-des-organisations/Theories-des-systemes/",
  "description": "Théories des systèmes",
  "fiche-a-completer": false,
  "fiche-publiee": true,
  "identifiant-drupal": 2290,
  "identifiant-drupal-parent": 2246,
  "mise-a-jour": "2017-01-23-16-33-30",
  "moment-de-creation": "2015-12-06-16-25-58",
  "moment-de-modification": "2015-01-04-02-27-39",
  "nom": "Théories des systèmes (organisations)",
  "nom-folder": "Theories-des-systemes",
  "nom-machine": [
    "terme-2015-12-06-16-25-58-86966229500"
  ],
  "parent": "terme-2015-12-06-16-25-55-86966229320",
  "sous-type": "sujets",
  "type": "taxonomies",
  "nomLangues": {
    "en": [
      "Systems theory (organizations)"
    ],
    "ar": [
      "نظرية الأنظمة"
    ],
    "es": [
      "Teoría de sistemas (organizaciones)"
    ],
    "fr": [
      "Théories des systèmes (organisations)"
    ],
    "it": [
      "Teorie dei sistemi (organizzazioni)"
    ]
  }
}