{
  "_id": "terme-2015-12-06-16-26-43-86966232191",
  "ajouter-aux-favoris": false,
  "breadcrumb": "taxonomies/sujets/Sciences-sociales/Anthropologie/Ethnographie/Ethnographie-economique/",
  "description": "Description de Ethnographie économique",
  "fiche-a-completer": true,
  "fiche-publiee": true,
  "identifiant-drupal": 451217,
  "identifiant-drupal-parent": 1026,
  "mise-a-jour": "2016-05-09-16-46-34",
  "moment-de-creation": "2015-12-06-16-26-43",
  "moment-de-modification": "2015-01-04-02-27-53",
  "nom": "Ethnographie économique",
  "nom-folder": "Ethnographie-economique",
  "nom-machine": "terme-2015-12-06-16-26-43-86966232191",
  "sous-type": "sujets",
  "type": "taxonomies",
  "nomLangues": {
    "en": [
      "Economic ethnography"
    ],
    "ar": [
      "الإثنوغرافيا الإقتصادية"
    ],
    "es": [
      "Etnografía económica"
    ],
    "fr": [
      "Ethnographie économique"
    ],
    "it": [
      "Etnografia economica"
    ]
  }
}