{
  "_id": "terme-2015-12-06-16-26-25-86966231127",
  "ajouter-aux-favoris": false,
  "breadcrumb": "taxonomies/sujets/Sciences-humaines/Geographie/Outils-et-techniques-en-geographie/Cartographie/",
  "description": "Description de Cartographie",
  "fiche-a-completer": false,
  "fiche-publiee": true,
  "identifiant-drupal": 970,
  "identifiant-drupal-parent": 948,
  "mise-a-jour": "2017-01-23-16-33-30",
  "moment-de-creation": "2015-12-06-16-26-25",
  "moment-de-modification": "2015-01-04-02-27-46",
  "nom": "Cartographie",
  "nom-folder": "Cartographie",
  "nom-machine": [
    "terme-2015-12-06-16-26-25-86966231127"
  ],
  "parent": "terme-2015-12-06-16-26-25-86966231121",
  "sous-type": "sujets",
  "type": "taxonomies",
  "nomLangues": {
    "en": [
      "Cartography"
    ],
    "ar": [
      "علم الخرائط"
    ],
    "es": [
      "Cartografía"
    ],
    "fr": [
      "Cartographie"
    ],
    "it": [
      "cartografia"
    ]
  }
}