{
  "_id": "terme-2015-12-06-16-26-33-86966231581",
  "ajouter-aux-favoris": false,
  "breadcrumb": "taxonomies/sujets/Sciences-humaines/Philosophie,-psychologie-et-religion/Philosophie/Philosophie-du-corps/",
  "description": "Description de Philosophie du corps",
  "fiche-a-completer": true,
  "fiche-publiee": true,
  "identifiant-drupal": 451243,
  "identifiant-drupal-parent": 270366,
  "mise-a-jour": "2016-05-09-16-46-32",
  "moment-de-creation": "2015-12-06-16-26-33",
  "moment-de-modification": "2015-01-04-02-27-46",
  "nom": "Philosophie du corps",
  "nom-folder": "Philosophie-du-corps",
  "nom-machine": [
    "terme-2015-12-06-16-26-33-86966231581"
  ],
  "sous-type": "sujets",
  "type": "taxonomies",
  "nomLangues": {
    "en": [
      "Philosophy of body"
    ],
    "ar": [
      "فلسفة الجسم"
    ],
    "es": [
      "Filosofía del cuerpo"
    ],
    "fr": [
      "Philosophie du corps"
    ],
    "it": [
      "filosofia del corpo"
    ]
  }
}