{
  "_id": "terme-2015-12-06-16-24-14-86966223267",
  "ajouter-aux-favoris": false,
  "breadcrumb": "taxonomies/sujets-JournalSeek/Psychology/Cross-Cultural-Psychology/",
  "description": "Description de Cross cultural psychology",
  "fiche-a-completer": true,
  "fiche-publiee": true,
  "identifiant-drupal": 369249,
  "identifiant-drupal-parent": 369241,
  "mise-a-jour": "2016-05-09-16-46-01",
  "moment-de-creation": "2015-12-06-16-24-14",
  "moment-de-modification": "2015-01-04-02-26-18",
  "nom": "Cross cultural psychology",
  "nom-folder": "Cross-Cultural-Psychology",
  "nom-machine": "terme-2015-12-06-16-24-14-86966223267",
  "sous-type": "sujets-JournalSeek",
  "type": "taxonomies",
  "nomLangues": {
    "fr": [
      "Cross cultural psychology"
    ]
  }
}