{
  "_id": "terme-2015-12-06-16-24-36-86966224598",
  "ajouter-aux-favoris": false,
  "breadcrumb": "taxonomies/sujets/Art/Arts-vivants/Theatre-(art)/Genres-theatraux/Comedie-(theatrale)/",
  "description": "Description de Comédie (théâtrale)",
  "fiche-a-completer": false,
  "fiche-publiee": true,
  "identifiant-drupal": 467065,
  "identifiant-drupal-parent": 467063,
  "mise-a-jour": "2017-01-23-16-33-30",
  "moment-de-creation": "2015-12-06-16-24-36",
  "moment-de-modification": "2015-01-04-02-27-51",
  "nom": "Comédie (théâtrale)",
  "nom-folder": "Comedie-(theatrale)",
  "nom-machine": "terme-2015-12-06-16-24-36-86966224598",
  "parent": "terme-2015-12-06-16-24-36-86966224592",
  "sous-type": "sujets",
  "type": "taxonomies",
  "nomLangues": {
    "en": [
      "Comedy"
    ],
    "ar": [
      "كوميديا (تمثيل مسرحي)"
    ],
    "es": [
      "Comedia"
    ],
    "fr": [
      "Comédie (théâtrale)"
    ],
    "it": [
      "Commedia (teatro)"
    ]
  }
}