{
  "_id": "terme-2015-12-06-16-26-23-86966230983",
  "ajouter-aux-favoris": false,
  "breadcrumb": "taxonomies/sujets/Sciences-humaines/Geographie/Amerique-Latine/",
  "description": "Description de Amérique Latine",
  "fiche-a-completer": false,
  "fiche-publiee": true,
  "identifiant-drupal": 270542,
  "identifiant-drupal-parent": 942,
  "mise-a-jour": "2017-01-23-16-33-30",
  "moment-de-creation": "2015-12-06-16-26-23",
  "moment-de-modification": "2015-01-04-02-27-46",
  "nom": "Amérique Latine",
  "nom-folder": "Amerique-Latine",
  "nom-machine": [
    "terme-2015-12-06-16-26-23-86966230983"
  ],
  "parent": "terme-2015-12-06-16-26-22-86966230968",
  "sous-type": "sujets",
  "type": "taxonomies",
  "nomLangues": {
    "en": [
      "Latin America"
    ],
    "ar": [
      "أمريكا اللاتينية"
    ],
    "es": [
      "América Latina"
    ],
    "fr": [
      "Amérique Latine"
    ],
    "it": [
      "America latina"
    ]
  }
}