{
  "_id": "terme-2015-12-06-16-24-46-86966225196",
  "ajouter-aux-favoris": false,
  "breadcrumb": "taxonomies/sujets/Art/Sociologie-de-l'art/",
  "description": "Description de Sociologie de l'art",
  "fiche-a-completer": true,
  "fiche-publiee": true,
  "identifiant-drupal": 467059,
  "identifiant-drupal-parent": 466753,
  "mise-a-jour": "2016-05-09-16-46-09",
  "moment-de-creation": "2015-12-06-16-24-46",
  "moment-de-modification": "2015-01-04-02-27-49",
  "nom": "Sociologie de l'art",
  "nom-folder": "Sociologie-de-l'art",
  "nom-machine": [
    "terme-2015-12-06-16-24-46-86966225196"
  ],
  "sous-type": "sujets",
  "type": "taxonomies",
  "nomLangues": {
    "en": [
      "Sociology of Art"
    ],
    "ar": [
      "علم اجتماع الفن"
    ],
    "es": [
      "Sociología del arte"
    ],
    "fr": [
      "Sociologie de l'art"
    ],
    "it": [
      "Sociologia dell'arte"
    ]
  }
}