{
  "_id": "terme-2015-12-06-16-24-34-86966224460",
  "ajouter-aux-favoris": false,
  "breadcrumb": "taxonomies/sujets/Art/Art-moderne/Expressionnisme/",
  "description": "Description de Expressionnisme",
  "fiche-a-completer": true,
  "fiche-publiee": true,
  "identifiant-drupal": 466857,
  "identifiant-drupal-parent": 466845,
  "mise-a-jour": "2016-05-09-16-46-06",
  "moment-de-creation": "2015-12-06-16-24-34",
  "moment-de-modification": "2015-01-04-02-27-50",
  "nom": "Expressionnisme",
  "nom-folder": "Expressionnisme",
  "nom-machine": [
    "terme-2015-12-06-16-24-34-86966224460"
  ],
  "sous-type": "sujets",
  "type": "taxonomies",
  "nomLangues": {
    "en": [
      "Expressionism"
    ],
    "ar": [
      "مذهب التعبيرية"
    ],
    "es": [
      "Expresionismo"
    ],
    "fr": [
      "Expressionnisme"
    ],
    "it": [
      "espressionismo"
    ]
  }
}