{
  "_id": "terme-2015-12-06-16-26-52-86966232752",
  "ajouter-aux-favoris": false,
  "breadcrumb": "taxonomies/sujets/Sciences-sociales/Sciences-politiques/Ideologies-politiques/Anarchisme-(ideologie)/Anarcho-capitalisme/",
  "description": "Description de Anarcho-capitalisme",
  "fiche-a-completer": true,
  "fiche-publiee": true,
  "identifiant-drupal": 1121,
  "identifiant-drupal-parent": 1112,
  "mise-a-jour": "2016-05-09-16-46-36",
  "moment-de-creation": "2015-12-06-16-26-52",
  "moment-de-modification": "2015-01-04-02-27-54",
  "nom": "Anarcho-capitalisme",
  "nom-folder": "Anarcho-capitalisme",
  "nom-machine": "terme-2015-12-06-16-26-52-86966232752",
  "sous-type": "sujets",
  "type": "taxonomies",
  "nomLangues": {
    "en": [
      "Anarcho-capitalism"
    ],
    "ar": [
      "لاسلطوية رأسمالية"
    ],
    "es": [
      "Anarcocapitalismo"
    ],
    "fr": [
      "Anarcho-capitalisme"
    ],
    "it": [
      "Anarco-capitalismo"
    ]
  }
}