{
  "_id": "terme-2015-12-06-16-23-50-86966221847",
  "ajouter-aux-favoris": false,
  "breadcrumb": "taxonomies/sujets-dialnet/Filologias/Linguistica/",
  "description": "Description de Linguistica",
  "fiche-a-completer": false,
  "fiche-publiee": true,
  "identifiant-drupal": 380919,
  "identifiant-drupal-parent": 380847,
  "mise-a-jour": "2017-01-23-16-33-30",
  "moment-de-creation": "2015-12-06-16-23-50",
  "moment-de-modification": "2015-01-04-02-27-56",
  "nom": "Linguistica",
  "nom-folder": "Linguistica",
  "nom-machine": "terme-2015-12-06-16-23-50-86966221847",
  "parent": "terme-2015-12-06-16-23-50-86966221828",
  "sous-type": "sujets-dialnet",
  "type": "taxonomies",
  "nomLangues": {
    "fr": [
      "Linguistica"
    ]
  }
}