{
  "_id": "terme-2015-12-06-16-23-36-86966220975",
  "ajouter-aux-favoris": false,
  "breadcrumb": "taxonomies/sections/La-societe/Debats/La-theocratie/",
  "description": "Description de La théocratie",
  "fiche-a-completer": false,
  "fiche-publiee": true,
  "identifiant-drupal": 1719,
  "identifiant-drupal-parent": 1671,
  "mise-a-jour": "2016-05-09-16-45-53",
  "moment-de-creation": "2015-12-06-16-23-36",
  "moment-de-modification": "2015-01-04-02-27-34",
  "nom": "La théocratie",
  "nom-folder": "La-theocratie",
  "nom-machine": [
    "terme-2015-12-06-16-23-36-86966220975"
  ],
  "sous-type": "sections",
  "type": "taxonomies",
  "nomLangues": {
    "en": [
      "Theocracy"
    ],
    "ar": [
      "الثيوقراطية"
    ],
    "es": [
      "La teocracia"
    ],
    "fr": [
      "La théocratie"
    ],
    "it": [
      "La teocrazia"
    ]
  }
}