{
  "_id": "terme-2015-12-06-16-26-11-86966230261",
  "ajouter-aux-favoris": false,
  "breadcrumb": "taxonomies/sujets/Sciences-economiques/Branches-de-l'economie/Analyse-economique/",
  "description": "Description de Analyse économique",
  "fiche-a-completer": false,
  "fiche-publiee": true,
  "identifiant-drupal": 1508,
  "identifiant-drupal-parent": 1492,
  "mise-a-jour": "2017-01-23-16-33-30",
  "moment-de-creation": "2015-12-06-16-26-11",
  "moment-de-modification": "2015-01-04-02-27-38",
  "nom": "Analyse économique",
  "nom-folder": "Analyse-economique",
  "nom-machine": [
    "terme-2015-12-06-16-26-11-86966230261"
  ],
  "parent": "terme-2015-12-06-16-26-10-86966230254",
  "sous-type": "sujets",
  "type": "taxonomies",
  "nomLangues": {
    "en": [
      "Economic Analysis"
    ],
    "ar": [
      "التحليل الاقتصادي"
    ],
    "es": [
      "Análisis económico"
    ],
    "fr": [
      "Analyse économique"
    ],
    "it": [
      "Analisi economica"
    ]
  }
}